LICENSE.md
MANIFEST.in
README.md
setup.py
django_classy_doc/__init__.py
django_classy_doc/app_settings.py
django_classy_doc/apps.py
django_classy_doc/urls.py
django_classy_doc/utils.py
django_classy_doc/views.py
django_classy_doc.egg-info/PKG-INFO
django_classy_doc.egg-info/SOURCES.txt
django_classy_doc.egg-info/dependency_links.txt
django_classy_doc.egg-info/requires.txt
django_classy_doc.egg-info/top_level.txt
django_classy_doc/management/commands/__init__.py
django_classy_doc/management/commands/classify.py
django_classy_doc/templates/django_classy_doc/base.html
django_classy_doc/templates/django_classy_doc/index.html
django_classy_doc/templates/django_classy_doc/klass.html
django_classy_doc/templates/django_classy_doc/show_checkboxes.html
django_classy_doc/templatetags/__init__.py
django_classy_doc/templatetags/classy_doc.py